LICENCE.txt
MANIFEST.in
README.rst
pyproject.toml
setup.cfg
setup.py
djangocms_lotus/__init__.py
djangocms_lotus/apps.py
djangocms_lotus/choices.py
djangocms_lotus/cms_plugins.py
djangocms_lotus/exceptions.py
djangocms_lotus/settings.py
djangocms_lotus.egg-info/PKG-INFO
djangocms_lotus.egg-info/SOURCES.txt
djangocms_lotus.egg-info/dependency_links.txt
djangocms_lotus.egg-info/requires.txt
djangocms_lotus.egg-info/top_level.txt
djangocms_lotus.egg-info/zip-safe
djangocms_lotus/compat/__init__.py
djangocms_lotus/compat/default_storage.py
djangocms_lotus/compat/import_zoneinfo.py
djangocms_lotus/factories/__init__.py
djangocms_lotus/factories/article.py
djangocms_lotus/factories/user.py
djangocms_lotus/forms/__init__.py
djangocms_lotus/forms/article.py
djangocms_lotus/migrations/0001_initial.py
djangocms_lotus/migrations/__init__.py
djangocms_lotus/models/__init__.py
djangocms_lotus/models/article.py
djangocms_lotus/plugins/__init__.py
djangocms_lotus/plugins/articleflux.py
djangocms_lotus/static/css/cmslotus-admin/article-flux.css
djangocms_lotus/static/css/cmslotus-admin/article-flux.css.map
djangocms_lotus/static/css/cmslotus-admin/lotus-admin.css
djangocms_lotus/templates/djangocms_lotus/article-flux/default.html
djangocms_lotus/utils/__init__.py
djangocms_lotus/utils/cms_tests.py
djangocms_lotus/utils/tests.py